fsu/concurrent.py
fsu/error.py
fsu/interceptor.py
fsu/internal/error.py
fsu/internal/error_code.py
fsu/mq.py
fsu/redcache.py
fsu/schema.py
fsu/security.py
fsu/service.py
fsu/sql.py
fsu/wx.py
fsu-3.1.1.dist-info/WHEEL
fsu-3.1.1.dist-info/METADATA
fsu-3.1.1.dist-info/RECORD
